Metadata-Version: 1.0
Name: z-distributions
Version: 0.1
Summary: Gaussian distributions
Home-page: UNKNOWN
Author: Chiazokam Echeta
Author-email: UNKNOWN
License: UNKNOWN
Platform: UNKNOWN
